LICENSE
MANIFEST.in
README.md
setup.cfg
setup.py
py_bangla_stemmer/__init__.py
py_bangla_stemmer.egg-info/PKG-INFO
py_bangla_stemmer.egg-info/SOURCES.txt
py_bangla_stemmer.egg-info/dependency_links.txt
py_bangla_stemmer.egg-info/not-zip-safe
py_bangla_stemmer.egg-info/top_level.txt
py_bangla_stemmer/resources/common.rules
py_bangla_stemmer/stemmer/__init__.py
py_bangla_stemmer/stemmer/rule_file_parser.py
py_bangla_stemmer/stemmer/stemmer.py