Metadata-Version: 1.1
Name: py-bangla-stemmer
Version: 0.5.1
Summary: Rule based Bengali Stemmer written in python
Home-page: https://github.com/sazid1462/py-bangla-stemmer
Author: Sazedul Islam
Author-email: sazidmailbox@gmail.com
License: GPL-3.0
Download-URL: https://github.com/sazid1462/py-bangla-stemmer/archive/v0.5.1.tar.gz
Keywords: stemmer,bengali-stemmer,bangla-stemmer,rule-based-stemmer,nlp
Platform: UNKNOWN
Classifier: Development Status :: 3 - Alpha
Classifier: Intended Audience :: Developers
Classifier: Natural Language :: Bengali
Classifier: Topic :: Text Processing :: Linguistic
Classifier: License :: OSI Approved :: GNU General Public License v3 (GPLv3)
Classifier: Programming Language :: Python :: 3
